<?xml version="1.0" encoding="UTF-8"?>
<analysisEngineDescription xmlns="http://uima.apache.org/resourceSpecifier">
  <frameworkImplementation>org.apache.uima.java</frameworkImplementation>
  <primitive>true</primitive>  <annotatorImplementationName>de.julielab.jcore.consumer.es.JsonWriter</annotatorImplementationName>
  <analysisEngineMetaData>
    <name>JCoRe JSON Consumer</name>
    <description/>
    <version>1.0</version>
    <vendor/>
    <configurationParameters>
      <configurationParameter>
        <name>OutputDir</name>
        <type>String</type>
        <multiValued>false</multiValued>
        <mandatory>true</mandatory>
      </configurationParameter>
    <configurationParameter>
        <name>GZIP</name>
        <description>If set to true, the JSON output will be GZIPped</description>
        <type>Boolean</type>
        <multiValued>false</multiValued>
        <mandatory>true</mandatory>
      </configurationParameter>
    <configurationParameter>
        <name>FilterBoards</name>
        <description>Class names of filter boards. A filter board is a simple Java class holding a range of filters as variables. Thus, the class is just a facility to group filters together so they can be used by field or document generators.</description>
        <type>String</type>
        <multiValued>true</multiValued>
        <mandatory>false</mandatory>
      </configurationParameter>
      <configurationParameter>
        <name>FieldGenerators</name>
        <description>Qualified class names of the field generators to run. A field generator is a class that adds fields to a document. The document will typically correspond to the CAS and the fields to some annotations.</description>
        <type>String</type>
        <multiValued>true</multiValued>
        <mandatory>false</mandatory>
      </configurationParameter>
      <configurationParameter>
        <name>DocumentGenerators</name>
        <description>Class names of document generators. Document generators are one step on top of field generators: Instead of only creating a number of fields for a single document, corresponding to the CAS, an arbitrary number of documents may be emitted by each document generator. For example, individual documents for each sentence of nominal phrase of a CAS could be generated.</description>
        <type>String</type>
        <multiValued>true</multiValued>
        <mandatory>false</mandatory>
      </configurationParameter>
    <configurationParameter>
        <name>IdField</name>
        <description>A field, generated by a field generator, whose value should be used as ElasticSearch document ID for the indexed document. Must be a single RawToken or PreanalyzedFieldValue. Does only apply for documents created by FieldGenerators. DocumentGenerators should set an ID of their own. The ID defaults to Header#docId().</description>
        <type>String</type>
        <multiValued>false</multiValued>
        <mandatory>false</mandatory>
      </configurationParameter>
      <configurationParameter>
        <name>IdPrefix</name>
        <description>A prefix to set to the document ID of the indexed ElasticSearch document.</description>
        <type>String</type>
        <multiValued>false</multiValued>
        <mandatory>false</mandatory>
      </configurationParameter>
    </configurationParameters>
    <configurationParameterSettings>
      <nameValuePair>
        <name>OutputDir</name>
        <value>
          <string>json-output</string>
        </value>
      </nameValuePair>
    <nameValuePair>
        <name>GZIP</name>
        <value>
          <boolean>true</boolean>
        </value>
      </nameValuePair>
    </configurationParameterSettings>
    <typeSystemDescription/>
    <typePriorities/>
    <fsIndexCollection/>
    <capabilities>
      <capability>
        <inputs/>
        <outputs/>
        <languagesSupported/>
      </capability>
    </capabilities>
  <operationalProperties>
      <modifiesCas>true</modifiesCas>
      <multipleDeploymentAllowed>true</multipleDeploymentAllowed>
      <outputsNewCASes>false</outputsNewCASes>
    </operationalProperties>
  </analysisEngineMetaData>
  <resourceManagerConfiguration/>
</analysisEngineDescription>
